openagent/__init__.py
openagent/config/__init__.py
openagent/config/config.py
openagent/core/__init__.py
openagent/core/llm.py
openagent/core/execution/__init__.py
openagent/core/execution/engine.py
openagent/core/execution/plan.py
openagent/core/persistence/__init__.py
openagent/core/persistence/manager.py
openagent/handlers/__init__.py
openagent/handlers/general_ai_agent.py
openagent/handlers/placeholders.py
openagent/handlers/sentinel_agent.py
openagent/models/__init__.py
openagent/models/execution.py
openagent/models/handlers.py
openagent/models/outputs.py
openagent/models/persistence.py
openagent/models/scheduling.py
openagent/models/sentinel.py
openagent/models/status_tracking.py
openagent/prompts/__init__.py
openagent/prompts/base.py
openagent/prompts/execution_planer.py
openagent/prompts/execution_sentinel.py
openagent/prompts/general_ai_agent.py
python_openagent-0.4.2.dist-info/METADATA
python_openagent-0.4.2.dist-info/WHEEL
python_openagent-0.4.2.dist-info/top_level.txt
python_openagent-0.4.2.dist-info/RECORD
