Metadata-Version: 2.4
Name: python-openagent
Version: 0.4.2
Summary: An agentic task execution framework for LLMs
Author-email: Bijay Regmi <bijay@regmi.dev>
Project-URL: Homepage, https://github.com/regmibijay/openagent
Project-URL: Documentation, https://regmibijay.github.io/openagent
Project-URL: Repository, https://github.com/regmibijay/openagent
Project-URL: Author Blog, https://blog.regmi.dev
Requires-Python: >=3.11
Requires-Dist: litellm>=1.77.4
Requires-Dist: matplotlib>=3.10.6
Requires-Dist: networkx>=3.5
Requires-Dist: openai>=1.109.1
Requires-Dist: pydantic>=2.11.9
Requires-Dist: pydantic-settings>=2.11.0
